py_book_util/__init__.py
py_book_util/__main__.py
py_book_util/command_pool.py
py_book_util/cross_page_recognizer.py
py_book_util/git_remote_book.py
py_book_util/image_recognizer.py
py_book_util/mirror.py
py_book_util/page_recognizer.py
py_book_util/string_buffer.py
py_book_util/util.py
py_book_util-0.1.66.dist-info/METADATA
py_book_util-0.1.66.dist-info/WHEEL
py_book_util-0.1.66.dist-info/RECORD
