Metadata-Version: 2.1
Name: py-book-util
Version: 0.1.66
Summary: 
Author: "Richard.Tang"
Author-email: tang_can@qq.com
Requires-Python: >=3.8,<4.0
Classifier: Programming Language :: Python :: 3
Classifier: Programming Language :: Python :: 3.8
Classifier: Programming Language :: Python :: 3.9
Classifier: Programming Language :: Python :: 3.10
Classifier: Programming Language :: Python :: 3.11
Requires-Dist: invoke (>=2.2.0,<3.0.0)
Requires-Dist: ipython (>=8.5.0,<9.0.0)
Requires-Dist: myst-nb (>=0.17.1,<0.18.0)
Requires-Dist: pillow (>=9.4.0,<10.0.0)
Requires-Dist: selenium (>=4.7.2,<5.0.0)
